MANIFEST.in
README
requirements.txt
setup.cfg
setup.py
redis_cache/__init__.py
redis_cache/cache.py
redis_cache.egg-info/PKG-INFO
redis_cache.egg-info/SOURCES.txt
redis_cache.egg-info/dependency_links.txt
redis_cache.egg-info/requires.txt
redis_cache.egg-info/top_level.txt