Metadata-Version: 1.0
Name: redis-cache
Version: 0.1.4
Summary: A data caching implemention based on Redis and redis_structures.
Home-page: https://github.com/jaredlunde/redis-cache
Author: Jared Lunde
Author-email: jared.lunde@gmail.com
License: MIT
Platform: UNKNOWN
